architext/__init__.py
architext/core.py
architext-0.1.74.dist-info/licenses/LICENSE
architext-0.1.74.dist-info/METADATA
architext-0.1.74.dist-info/WHEEL
architext-0.1.74.dist-info/top_level.txt
architext-0.1.74.dist-info/RECORD
