Metadata-Version: 2.4
Name: architext
Version: 0.1.74
Summary: The Context Engineering framework for building smarter, more reliable AI Agents.
Requires-Python: >=3.11
License-File: LICENSE
Dynamic: license-file
